README.md
setup.cfg
setup.py
rm_gaussian_binomial_distributions/Binomialdistribution.py
rm_gaussian_binomial_distributions/Gaussiandistribution.py
rm_gaussian_binomial_distributions/Generaldistribution.py
rm_gaussian_binomial_distributions/__init__.py
rm_gaussian_binomial_distributions.egg-info/PKG-INFO
rm_gaussian_binomial_distributions.egg-info/SOURCES.txt
rm_gaussian_binomial_distributions.egg-info/dependency_links.txt
rm_gaussian_binomial_distributions.egg-info/not-zip-safe
rm_gaussian_binomial_distributions.egg-info/top_level.txt