Metadata-Version: 1.0
Name: rm-gaussian-binomial-distributions
Version: 0.1
Summary: Gaussian and Binomial distributions
Home-page: UNKNOWN
Author: Rashmi Maharjan
Author-email: rashmisinghmaharjan@gmail.com
License: UNKNOWN
Platform: UNKNOWN
